grad_watch/__init__.py
grad_watch/main.py
grad_watch-0.1.dist-info/METADATA
grad_watch-0.1.dist-info/WHEEL
grad_watch-0.1.dist-info/top_level.txt
grad_watch-0.1.dist-info/RECORD
